eduML/__init__.py
eduML/core/__init__.py
eduML/core/dataset_loader.py
eduML/core/metrics.py
eduML/core/preprocessing.py
eduML/core/visualize.py
eduML/experiments/__init__.py
eduML/explainers/__init__.py
eduML/explainers/explain_utils.py
eduML/interface/__init__.py
eduML/interface/cli.py
eduML/interface/config_manager.py
eduML/interface/data_utils.py
eduML/interface/model_aliases.py
eduML/interface/model_builder.py
eduML/metrics/__init__.py
eduML/metrics/classification_metrics.py
eduML/metrics/regression_metrics.py
eduML/metrics/visualize.py
eduML/supervised/__init__.py
eduML/supervised/decision_tree.py
eduML/supervised/knn.py
eduML/supervised/lda.py
eduML/supervised/linear_regression.py
eduML/supervised/logistic_regression.py
eduML/supervised/naive_bayes.py
eduML/supervised/neural_network.py
eduML/supervised/ridge_regression.py
eduML/supervised/svm.py
eduML/unsupervised/__init__.py
eduML/unsupervised/kmeans.py
eduML/unsupervised/pca.py
eduml-1.0.11.dist-info/licenses/LICENSE
eduml-1.0.11.dist-info/METADATA
eduml-1.0.11.dist-info/WHEEL
eduml-1.0.11.dist-info/top_level.txt
eduml-1.0.11.dist-info/RECORD
